pyfetion
